loaderx/__init__.py
loaderx/dataloader.py
loaderx/dataset.py
loaderx-0.1.2.dist-info/licenses/LICENSE
loaderx-0.1.2.dist-info/METADATA
loaderx-0.1.2.dist-info/WHEEL
loaderx-0.1.2.dist-info/top_level.txt
loaderx-0.1.2.dist-info/RECORD
