Metadata-Version: 2.4
Name: loaderx
Version: 0.1.2
Summary: Minimal data loader for Flax
Author-email: Ben0i0d <ben0i0d@foxmail.com>
License: MIT License
Project-URL: Homepage, https://github.com/eoeair/loaderx
Project-URL: Documentation, https://github.com/eoeair/loaderx
Project-URL: Source, https://github.com/eoeair/loaderx
Project-URL: Bug Tracker, https://github.com/eoeair/loaderx/issues
Keywords: flax,python,dataloader
Classifier: Development Status :: 3 - Alpha
Classifier: Intended Audience :: Developers
Classifier: License :: OSI Approved :: MIT License
Classifier: Programming Language :: Python :: 3
Requires-Python: >=3.10
License-File: LICENSE
Requires-Dist: numpy
Dynamic: license-file
